README.md
setup.py
inasafe_parameters.egg-info/PKG-INFO
inasafe_parameters.egg-info/SOURCES.txt
inasafe_parameters.egg-info/dependency_links.txt
inasafe_parameters.egg-info/top_level.txt
parameters/__init__.py
parameters/boolean_parameter.py
parameters/collection_parameter.py
parameters/dict_parameter.py
parameters/float_parameter.py
parameters/generic_parameter.py
parameters/group_parameter.py
parameters/input_list_parameter.py
parameters/integer_parameter.py
parameters/list_parameter.py
parameters/metadata.py
parameters/numeric_parameter.py
parameters/parameter_exceptions.py
parameters/registry.py
parameters/select_parameter.py
parameters/string_parameter.py
parameters/text_parameter.py
parameters/unit.py
parameters/html_widgets/__init__.py
parameters/qt_widgets/__init__.py
parameters/qt_widgets/boolean_parameter_widget.py
parameters/qt_widgets/dict_parameter_widget.py
parameters/qt_widgets/float_parameter_widget.py
parameters/qt_widgets/generic_parameter_widget.py
parameters/qt_widgets/group_parameter_widget.py
parameters/qt_widgets/input_list_parameter_widget.py
parameters/qt_widgets/integer_parameter_widget.py
parameters/qt_widgets/list_parameter_widget.py
parameters/qt_widgets/numeric_parameter_widget.py
parameters/qt_widgets/parameter_container.py
parameters/qt_widgets/qt5_parameter_factory.py
parameters/qt_widgets/select_parameter_widget.py
parameters/qt_widgets/string_parameter_widget.py
parameters/qt_widgets/text_parameter_widget.py
parameters/qt_widgets/test/__init__.py
parameters/qt_widgets/test/main.py
parameters/qt_widgets/test/resource_example.py
parameters/qt_widgets/test/test_boolean_parameter_widget.py
parameters/qt_widgets/test/test_float_parameter_widget.py
parameters/qt_widgets/test/test_integer_parameter_widget.py
parameters/qt_widgets/test/test_qt5_parameter_factory.py
parameters/qt_widgets/test/test_select_parameter_widget.py
parameters/qt_widgets/test/test_string_parameter_widget.py
parameters/qt_widgets/test/custom_parameter/__init__.py
parameters/qt_widgets/test/custom_parameter/point_parameter.py
parameters/qt_widgets/test/custom_parameter/point_parameter_widget.py
parameters/test/__init__.py
