Metadata-Version: 1.1
Name: inasafe-parameters
Version: 2.0.0
Summary: A generic package for capturing and validating user parameters
Home-page: http://inasafe.org/
Author: InaSAFE Team
Author-email: info@inasafe.org
License: GPL
Platform: UNKNOWN
Classifier: Development Status :: 5 - Production/Stable
Classifier: Intended Audience :: Developers
Classifier: Intended Audience :: Science/Research
Classifier: License :: OSI Approved :: GNU General Public License v3 (GPLv3)
Classifier: Operating System :: OS Independent
Classifier: Programming Language :: Python
Classifier: Topic :: Scientific/Engineering :: GIS
